vereqsyn/__about__.py
vereqsyn/__init__.py
vereqsyn/__main__.py
vereqsyn-1.1.dist-info/METADATA
vereqsyn-1.1.dist-info/WHEEL
vereqsyn-1.1.dist-info/entry_points.txt
vereqsyn-1.1.dist-info/licenses/LICENSE
vereqsyn-1.1.dist-info/RECORD
