Metadata-Version: 2.4
Name: vereqsyn
Version: 1.1
Summary: Bi-directional version.cfg <–> requirements.txt synchronization
Project-URL: Documentation, https://github.com/minddistrict/vereqsyn#readme
Project-URL: Issues, https://github.com/minddistrict/vereqsyn/issues
Project-URL: Source, https://github.com/minddistrict/vereqsyn
Project-URL: changelog, https://github.com/minddistrict/vereqsyn/blob/master/CHANGES.md
Author-email: Michael Howitz <icemac@gmx.net>
License-Expression: MIT
License-File: LICENSE
Classifier: Development Status :: 4 - Beta
Classifier: Programming Language :: Python
Classifier: Programming Language :: Python :: 3.11
Classifier: Programming Language :: Python :: 3.12
Classifier: Programming Language :: Python :: Implementation :: CPython
Requires-Python: >=3.11
Requires-Dist: packaging
